{
  "sound_change_modern_to_ancient": {
    "triều": "trều",
    "chiên": "chên",
    "chuyến": "chuến",
    "huyết": "huét",
    "huyện": "huện",
    "phiên": "phén",
    "duyệt": "duyệt",
    "huyền": "huền",
    "luyện": "luện",
    "rưới": "rói",
    "vuột/suốt": "vọt",
    "ngược": "ngóc",
    "đều": "điều",
    "phết": "phiết",
    "thuê": "thuyê",
    "vịt": "việt",
    "gửi": "gởi",
    "rưới/rửi": "rổi",
    "bồi": "buôi",
    "với": "vuối",
    "bặm": "bạm",
    "cắm": "cám",
    "đắm": "đam",
    "mắm": "mâm",
    "năm": "nam",
    "chẳng": "cháng",
    "đẳng": "đắng",
    "trắng": "tráng",
    "vắng": "váng",
    "chặt": "chát",
    "mặt": "mát",
    "sặt": "sát",
    "bắc": "bác",
    "đặc": "đặc",
    "rắc": "rác",
    "nắt": "nát",
    "đăng": "đong",
    "băng": "bong",
    "nắng": "nóng",
    "văng": "vong",
    "tắc": "tóc",
    "gắc": "góc",
    "bặc": "bọc",
    "ong": "aong",
    "bong": "baong",
    "chong": "chaong",
    "đong": "đaong",
    "song": "saong",
    "thong": "thaong",
    "vong": "vaong",
    "bóc": "báoc",
    "chọc": "chạoc",
    "đọc": "đạoc",
    "lọc": "lạoc",
    "mọc": "mạoc",
    "nọc": "nạoc",
    "thọc": "thạoc",
    "bay": "băy",
    "bấy": "băy",
    "bây": "băy",
    "dạy / dày": "dầy",
    "cày": "căy",
    "chạy": "chăy",
    "cháy": "chăy",
    "chậy": "chăy",
    "dẫy": "dăy",
    "đầy / đày": "đầy",
    "đấy": "đấy",
    "gãy": "gẫy",
    "hay": "hăy",
    "hãy": "hăy",
    "lấy": "lăy",
    "may": "măy",
    "mày": "măy",
    "này": "năy",
    "nhảy": "nhăy",
    "ngày": "ngăy",
    "quay": "quăy",
    "rảy": "răy",
    "rẫy": "răy",
    "tay": "tăy"
  },
  "sound_change_ancient_to_modern": {
    "trều": "triều",
    "chên": "chiên",
    "chuến": "chuyến",
    "huét": "huyết",
    "huện": "huyện",
    "phén": "phiên",
    "duyệt": "duyệt",
    "huền": "huyền",
    "luện": "luyện",
    "rói": "rưới",
    "vọt": "vuột/suốt",
    "ngóc": "ngược",
    "điều": "đều",
    "phiết": "phết",
    "thuyê": "thuê",
    "việt": "vịt",
    "gởi": "gửi",
    "rổi": "rưới/rửi",
    "buôi": "bồi",
    "vuối": "với",
    "bạm": "bặm",
    "cám": "cắm",
    "đam": "đắm",
    "mâm": "mắm",
    "nam": "năm",
    "cháng": "chẳng",
    "đắng": "đẳng",
    "tráng": "trắng",
    "váng": "vắng",
    "chát": "chặt",
    "mát": "mặt",
    "sát": "sặt",
    "bác": "bắc",
    "đặc": "đặc",
    "rác": "rắc",
    "nát": "nắt",
    "đong": "đăng",
    "bong": "băng",
    "nóng": "nắng",
    "vong": "văng",
    "tóc": "tắc",
    "góc": "gắc",
    "bọc": "bặc",
    "aong": "ong",
    "baong": "bong",
    "chaong": "chong",
    "đaong": "đong",
    "saong": "song",
    "thaong": "thong",
    "vaong": "vong",
    "báoc": "bóc",
    "chạoc": "chọc",
    "đạoc": "đọc",
    "lạoc": "lọc",
    "mạoc": "mọc",
    "nạoc": "nọc",
    "thạoc": "thọc",
    "băy": "bây",
    "dầy": "dạy / dày",
    "căy": "cày",
    "chăy": "chậy",
    "dăy": "dẫy",
    "đầy": "đầy / đày",
    "đấy": "đấy",
    "gẫy": "gãy",
    "hăy": "hãy",
    "lăy": "lấy",
    "măy": "mày",
    "năy": "này",
    "nhăy": "nhảy",
    "ngăy": "ngày",
    "quăy": "quay",
    "răy": "rẫy",
    "tăy": "tay"
  },
  "vocabulary_modern_to_ancient": {
    "Còn như": "Bằng",
    "còn": "Bằng",
    "Gây vạ": "Bỏ vạ",
    "để vạ cho": "Bỏ vạ",
    "Bản quốc": "Bổn cuốc",
    "nước mình": "Bổn cuốc",
    "Cả": "Cả và",
    "tất cả": "Cả và",
    "Báo": "Cáo",
    "nói với": "Cáo",
    "Nhờ": "Cậy",
    "nhờ cậy": "Cậy",
    "Cừu": "Chiên",
    "Trình": "Chiềng",
    "thưa": "Chiềng",
    "bẩm": "Chiềng",
    "Liên tục": "Cho liền",
    "thường xuyên": "Cho liền",
    "Mưu": "Chước",
    "kế": "Chước",
    "Cuốn": "Con",
    "quyển": "Con",
    "Mắng mỏ": "Đức lác",
    "nhiếc móc": "Đức lác",
    "Đường sá": "Đàng sá",
    "Dọa nạt": "Đe loi",
    "cái gì / chút gì": "Đỉ gì",
    "Xong (rồi mới)": "Đoạn (mới)",
    "sau đó (mới)": "Đoạn (mới)",
    "Giã biệt": "Giả",
    "tạm biệt": "Giả",
    "từ biệt": "Giả",
    "Gửi": "Gưởi",
    "Gần": "Hầu",
    "gần như": "Hầu",
    "Kinh thành": "Kẻ chợ",
    "thủ đô": "Kẻ chợ",
    "Người bệnh": "Kẻ liệt",
    "Bí mật": "Kín nhiệm",
    "kín đáo": "Kín nhiệm",
    "Tìm cách": "Làm chước",
    "bày trò": "Làm chước",
    "Gây khó khăn": "Làm khốn",
    "trở ngại": "Làm khốn",
    "làm cho khốn đốn": "Làm khốn",
    "Lương": "Lang",
    "Mặc lòng": "Mặc làoòng",
    "tùy ý": "Mặc làoòng",
    "mặc kệ": "Mặc làoòng",
    "Đất": "Mắt, mắt mờ",
    "đất đỏ": "Mắt, mắt mờ",
    "Chỉ": "Một",
    "duy chỉ": "Một",
    "Một lần": "Một trật",
    "Ngửi": "Người",
    "Gặp": "Phải",
    "mắc phải": "Phải",
    "bị": "Phải",
    "Các": "Phô",
    "lũ": "Phô",
    "chúng": "Phô",
    "Ban": "Phú",
    "cho": "Phú",
    "Huống hồ": "Phương chi",
    "Trở nên": "Ra",
    "thành ra": "Ra",
    "Nay": "Rầy",
    "Sao": "Ru",
    "hay sao": "Ru",
    "Tuy nhiên": "Saong le",
    "Quý mến": "Sốt mến",
    "Tốn kém": "Sở tổn",
    "Tất cả": "Thầy thầy",
    "Linh mục": "Thầy cả",
    "Hoàng đế": "Thượng vị",
    "Trường": "Tràng",
    "Quan trọng": "Traọng",
    "lớn": "Traọng",
    "Định đi": "Tuan trẩy",
    "định lên đường": "Tuan trẩy",
    "Tuyền": "Tuền",
    "toàn là": "Tuền",
    "Diệt": "Tuệt",
    "chấm dứt": "Tuệt",
    "hết": "Tuệt",
    "Hàng dệt bằng to": "Vaóc",
    "có hoa văn": "Vaóc"
  },
  "vocabulary_ancient_to_modern": {
    "Bằng": [
      "Còn như",
      "còn"
    ],
    "Bỏ vạ": [
      "Gây vạ",
      "để vạ cho"
    ],
    "Bổn cuốc": [
      "Bản quốc",
      "nước mình"
    ],
    "Cả và": [
      "Cả",
      "tất cả"
    ],
    "Cáo": [
      "Báo",
      "nói với"
    ],
    "Cậy": [
      "Nhờ",
      "nhờ cậy"
    ],
    "Chiên": [
      "Cừu"
    ],
    "Chiềng": [
      "Trình",
      "thưa",
      "bẩm"
    ],
    "Cho liền": [
      "Liên tục",
      "thường xuyên"
    ],
    "Chước": [
      "Mưu",
      "kế"
    ],
    "Con": [
      "Cuốn",
      "quyển"
    ],
    "Đức lác": [
      "Mắng mỏ",
      "nhiếc móc"
    ],
    "Đàng sá": [
      "Đường sá"
    ],
    "Đe loi": [
      "Dọa nạt"
    ],
    "Đỉ gì": [
      "cái gì / chút gì"
    ],
    "Đoạn (mới)": [
      "Xong (rồi mới)",
      "sau đó (mới)"
    ],
    "Giả": [
      "Giã biệt",
      "tạm biệt",
      "từ biệt"
    ],
    "Gưởi": [
      "Gửi"
    ],
    "Hầu": [
      "Gần",
      "gần như"
    ],
    "Kẻ chợ": [
      "Kinh thành",
      "thủ đô"
    ],
    "Kẻ liệt": [
      "Người bệnh"
    ],
    "Kín nhiệm": [
      "Bí mật",
      "kín đáo"
    ],
    "Làm chước": [
      "Tìm cách",
      "bày trò"
    ],
    "Làm khốn": [
      "Gây khó khăn",
      "trở ngại",
      "làm cho khốn đốn"
    ],
    "Lang": [
      "Lương"
    ],
    "Mặc làoòng": [
      "Mặc lòng",
      "tùy ý",
      "mặc kệ"
    ],
    "Mắt, mắt mờ": [
      "Đất",
      "đất đỏ"
    ],
    "Một": [
      "Chỉ",
      "duy chỉ"
    ],
    "Một trật": [
      "Một lần"
    ],
    "Người": [
      "Ngửi"
    ],
    "Phải": [
      "Gặp",
      "mắc phải",
      "bị"
    ],
    "Phô": [
      "Các",
      "lũ",
      "chúng"
    ],
    "Phú": [
      "Ban",
      "cho"
    ],
    "Phương chi": [
      "Huống hồ"
    ],
    "Ra": [
      "Trở nên",
      "thành ra"
    ],
    "Rầy": [
      "Nay"
    ],
    "Ru": [
      "Sao",
      "hay sao"
    ],
    "Saong le": [
      "Tuy nhiên"
    ],
    "Sốt mến": [
      "Quý mến"
    ],
    "Sở tổn": [
      "Tốn kém"
    ],
    "Thầy thầy": [
      "Tất cả"
    ],
    "Thầy cả": [
      "Linh mục"
    ],
    "Thượng vị": [
      "Hoàng đế"
    ],
    "Tràng": [
      "Trường"
    ],
    "Traọng": [
      "Quan trọng",
      "lớn"
    ],
    "Tuan trẩy": [
      "Định đi",
      "định lên đường"
    ],
    "Tuền": [
      "Tuyền",
      "toàn là"
    ],
    "Tuệt": [
      "Diệt",
      "chấm dứt",
      "hết"
    ],
    "Vaóc": [
      "Hàng dệt bằng to",
      "có hoa văn"
    ]
  },
  "fixed_phrases_modern_to_ancient": {
    "Mạnh ai nấy thắng, ai có quyền lực thì chiếm được lợi thế.": "Ai mạnh nấy được",
    "Không biết lòng mình, chỉ lo việc ngoài, thiếu tự tỉnh.": "Bất tri kỷ tâm",
    "Cha làm nghề gì, con nối nghiệp đó; ám chỉ hệ thống cha truyền con nối.": "Cha làm quan nào thì con lại làm quan nấy",
    "Chỉ sự bận rộn, hoạt động khắp nơi.": "Chạy ngang chạy dọc",
    "Tiếng trống vang, báo hiệu lễ hội hoặc sự kiện lớn.": "Chiềng kêu",
    "Chỉ người có phúc, sống sung túc, đủ đầy.": "Cơm nặng áo dầy",
    "Quan lớn, người có công lao hiển hách, quyền uy trong triều.": "Công thần phiệt duyệt",
    "Chỉ người không nhất quán, thay đổi lòng dạ, gió chiều nào che chiều ấy.": "Đi chu tâm chu, đi mã tâm mã",
    "Thuốc đắng dã tật, lời thật mất lòng; cái tốt thường khó chịu nhưng có lợi.": "Độc dược khổ khẩu",
    "Đạt được điều mình muốn rồi thì bỏ phương tiện, không còn cần đến nữa.": "Được cá bỏ nơm",
    "Phong tục man rợ: con giết cha mẹ già; ẩn dụ chỉ đạo đức suy đồi.": "Huệ̂t cư dạ xứ",
    "Cuộc đời có lúc hưng thịnh, lúc suy tàn.": "Khi thịnh khi suy",
    "Chỉ người bận rộn, lo toan nhiều việc trong nhà.": "Mắt mờ cửa nhà",
    "Chỉ người độc miệng, thâm độc, nói lời cay nghiệt.": "Miệng đắng lưỡi rắn",
    "Trơn tru, bóng bẩy, sạch sẽ; cũng có thể ẩn dụ người khéo léo, trơn tru.": "Nhẵn như gương",
    "Một vợ một chồng, trung thủy, đạo đức.": "Nhất phu nhất phụ",
    "Trẻ không dạy dỗ sớm thì lớn khó sửa nết.": "Non chẳng uốn, già bẻ gãy ngành",
    "Nuôi kẻ phản bội, giúp người rồi bị hại lại.": "Nuôi ong tay áo",
    "Chỉ sóng gió, biến động lớn, khó khăn trùng trùng.": "Phaong ba bão táp",
    "Đạo vợ chồng xưa: vợ theo chồng, phụ thuộc chồng.": "Phu sướng phụ tùy",
    "Quan nghiêm khắc, xử lý công minh, cứng rắn.": "Quan hình sát sắc",
    "Kẻ địch bên cạnh, người đối lập hoặc cạnh tranh trực tiếp.": "Quan kỳ địch tác",
    "Thân quen thì dễ nói chuyện, xa lạ thì giữ kẽ.": "Quen thì dài dạ, lạ thì dài áo",
    "Chỉ sự ràng buộc chặt chẽ, khó gỡ bỏ.": "Rễ bằng rễ bám",
    "Tổn hao công sức, vất vả vì công vụ.": "Sở tổn công lệnh",
    "Người xấu được cảm hóa trở nên hiền lành.": "Sói dữ ra lành",
    "Tự hạ mình, khiêm tốn, nói bản thân kém cỏi.": "Tài yếu sức mọn",
    "Hết đường xoay xở, bế tắc, không còn kế nào khác.": "Tận lang vô kế",
    "Mười tám nước chư hầu cùng theo đạo; chỉ sự đồng lòng, quy thuận.": "Thập bát cuốc chư hầu",
    "Núi ngàn sông vạn, chỉ sự xa xôi, cách trở.": "Thiên sơn vạn thủy",
    "Kẻ yếu bị vạ lây khi người mạnh tranh chấp.": "Trâu bò húc nhau thì ruồi muỗi phải khốn",
    "Lời ngay thẳng thường khó nghe, nhưng có lợi.": "Trung ngôn nghịch nhĩ",
    "Chỉ nợ nần chồng chất, mắc ơn nghĩa khắp nơi.": "Vay công mượn nợ",
    "Vạn vật có bản thể thật, chỉ chân lý vũ trụ, nguyên lý tối sơ.": "Vạn vật chân nguyên"
  },
  "fixed_phrases_ancient_to_modern": {
    "Ai mạnh nấy được": "Mạnh ai nấy thắng, ai có quyền lực thì chiếm được lợi thế.",
    "Bất tri kỷ tâm": "Không biết lòng mình, chỉ lo việc ngoài, thiếu tự tỉnh.",
    "Cha làm quan nào thì con lại làm quan nấy": "Cha làm nghề gì, con nối nghiệp đó; ám chỉ hệ thống cha truyền con nối.",
    "Chạy ngang chạy dọc": "Chỉ sự bận rộn, hoạt động khắp nơi.",
    "Chiềng kêu": "Tiếng trống vang, báo hiệu lễ hội hoặc sự kiện lớn.",
    "Cơm nặng áo dầy": "Chỉ người có phúc, sống sung túc, đủ đầy.",
    "Công thần phiệt duyệt": "Quan lớn, người có công lao hiển hách, quyền uy trong triều.",
    "Đi chu tâm chu, đi mã tâm mã": "Chỉ người không nhất quán, thay đổi lòng dạ, gió chiều nào che chiều ấy.",
    "Độc dược khổ khẩu": "Thuốc đắng dã tật, lời thật mất lòng; cái tốt thường khó chịu nhưng có lợi.",
    "Được cá bỏ nơm": "Đạt được điều mình muốn rồi thì bỏ phương tiện, không còn cần đến nữa.",
    "Huệ̂t cư dạ xứ": "Phong tục man rợ: con giết cha mẹ già; ẩn dụ chỉ đạo đức suy đồi.",
    "Khi thịnh khi suy": "Cuộc đời có lúc hưng thịnh, lúc suy tàn.",
    "Mắt mờ cửa nhà": "Chỉ người bận rộn, lo toan nhiều việc trong nhà.",
    "Miệng đắng lưỡi rắn": "Chỉ người độc miệng, thâm độc, nói lời cay nghiệt.",
    "Nhẵn như gương": "Trơn tru, bóng bẩy, sạch sẽ; cũng có thể ẩn dụ người khéo léo, trơn tru.",
    "Nhất phu nhất phụ": "Một vợ một chồng, trung thủy, đạo đức.",
    "Non chẳng uốn, già bẻ gãy ngành": "Trẻ không dạy dỗ sớm thì lớn khó sửa nết.",
    "Nuôi ong tay áo": "Nuôi kẻ phản bội, giúp người rồi bị hại lại.",
    "Phaong ba bão táp": "Chỉ sóng gió, biến động lớn, khó khăn trùng trùng.",
    "Phu sướng phụ tùy": "Đạo vợ chồng xưa: vợ theo chồng, phụ thuộc chồng.",
    "Quan hình sát sắc": "Quan nghiêm khắc, xử lý công minh, cứng rắn.",
    "Quan kỳ địch tác": "Kẻ địch bên cạnh, người đối lập hoặc cạnh tranh trực tiếp.",
    "Quen thì dài dạ, lạ thì dài áo": "Thân quen thì dễ nói chuyện, xa lạ thì giữ kẽ.",
    "Rễ bằng rễ bám": "Chỉ sự ràng buộc chặt chẽ, khó gỡ bỏ.",
    "Sở tổn công lệnh": "Tổn hao công sức, vất vả vì công vụ.",
    "Sói dữ ra lành": "Người xấu được cảm hóa trở nên hiền lành.",
    "Tài yếu sức mọn": "Tự hạ mình, khiêm tốn, nói bản thân kém cỏi.",
    "Tận lang vô kế": "Hết đường xoay xở, bế tắc, không còn kế nào khác.",
    "Thập bát cuốc chư hầu": "Mười tám nước chư hầu cùng theo đạo; chỉ sự đồng lòng, quy thuận.",
    "Thiên sơn vạn thủy": "Núi ngàn sông vạn, chỉ sự xa xôi, cách trở.",
    "Trâu bò húc nhau thì ruồi muỗi phải khốn": "Kẻ yếu bị vạ lây khi người mạnh tranh chấp.",
    "Trung ngôn nghịch nhĩ": "Lời ngay thẳng thường khó nghe, nhưng có lợi.",
    "Vay công mượn nợ": "Chỉ nợ nần chồng chất, mắc ơn nghĩa khắp nơi.",
    "Vạn vật chân nguyên": "Vạn vật có bản thể thật, chỉ chân lý vũ trụ, nguyên lý tối sơ."
  }
}